README.md
setup.py
pyormx/PooledDB.py
pyormx/Pools.py
pyormx/SteadyDB.py
pyormx/__init__.py
pyormx/constant.py
pyormx/example.py
pyormx/orm.py
pyormx/sql_utils.py
pyormx.egg-info/PKG-INFO
pyormx.egg-info/SOURCES.txt
pyormx.egg-info/dependency_links.txt
pyormx.egg-info/top_level.txt