Metadata-Version: 1.0
Name: pyormx
Version: 0.2.1
Summary: python简易ORM框架
Home-page: https://github.com/xingluoxingkong/pyormx
Author: xlxk
Author-email: xlxk@xlxk.top
License: MIT Licence
Keywords: pip,pathtool,timetool,magetool,mage
Platform: any
